gsocketio/Instance.py
gsocketio/__init__.py
gsocketio/Utils/LogManager.py
gsocketio/Utils/Payload.py
gsocketio/Utils/Typing.py
gsocketio/Utils/Wrapper.py
gsocketio/Utils/__init__.py
GSocketIO-0.1.1.dist-info/LICENSE
GSocketIO-0.1.1.dist-info/METADATA
GSocketIO-0.1.1.dist-info/WHEEL
GSocketIO-0.1.1.dist-info/top_level.txt
GSocketIO-0.1.1.dist-info/RECORD
