Metadata-Version: 2.2
Name: GSocketIO
Version: 0.1.1
Summary: Flask-SocketIOの設定を簡素化するラッパー。
Author-email: げるすらいむ <contact@mail.gerusuraimu.com>
License: MIT License
License-File: LICENSE
Requires-Dist: flask
Requires-Dist: flask-socketio
Requires-Dist: numpy
Requires-Dist: pillow
Requires-Dist: opencv-python
